README.md
setup.py
object_summary/__init__.py
object_summary/analysis.py
object_summary/similarity.py
object_summary/util.py
object_summary.egg-info/PKG-INFO
object_summary.egg-info/SOURCES.txt
object_summary.egg-info/dependency_links.txt
object_summary.egg-info/not-zip-safe
object_summary.egg-info/requires.txt
object_summary.egg-info/top_level.txt