Metadata-Version: 1.0
Name: object-summary
Version: 0.2.2
Summary: A library that makes use of object detection to provide insights into image data.
Home-page: https://github.com/UMass-Rescue/object_summary
Author: Prasanna Lakkur Subramanyam
Author-email: prasanna.lakkur@gmail.com
License: UNKNOWN
Platform: UNKNOWN
